setup.py
vkbotsapi/__init__.py
vkbotsapi/api.py
vkbotsapi.egg-info/PKG-INFO
vkbotsapi.egg-info/SOURCES.txt
vkbotsapi.egg-info/dependency_links.txt
vkbotsapi.egg-info/not-zip-safe
vkbotsapi.egg-info/top_level.txt