Metadata-Version: 1.0
Name: vkbotsapi
Version: 0.0.3
Summary: VK API module for Python
Home-page: https://github.com/wultes/vkbotsapi
Author: Wultes (Kirill)
Author-email: wultesu@gmail.com
License: MIT
Platform: UNKNOWN
